downscale/__init__.py
downscale/cli.py
downscale/downscale.py
downscale-0.0.1.dist-info/DESCRIPTION.rst
downscale-0.0.1.dist-info/METADATA
downscale-0.0.1.dist-info/RECORD
downscale-0.0.1.dist-info/WHEEL
downscale-0.0.1.dist-info/entry_points.txt
downscale-0.0.1.dist-info/metadata.json
downscale-0.0.1.dist-info/top_level.txt
