Metadata-Version: 2.0
Name: downscale
Version: 0.0.1
Summary: Tools for downscaling gridded data in xarray
Home-page: https://github.com/ClimateImpactLab/downscale
Author: Michael Delgado
Author-email: mdelgado@rhg.com
License: MIT license
Keywords: downscale
Platform: UNKNOWN
Classifier: Development Status :: 2 - Pre-Alpha
Classifier: Intended Audience :: Developers
Classifier: License :: OSI Approved :: MIT License
Classifier: Natural Language :: English
Classifier: Programming Language :: Python :: 2
Classifier: Programming Language :: Python :: 2.7
Classifier: Programming Language :: Python :: 3
Classifier: Programming Language :: Python :: 3.3
Classifier: Programming Language :: Python :: 3.4
Classifier: Programming Language :: Python :: 3.5
Requires-Dist: Click (>=6.0)
